{"nodes":[{"id":"AUDIT_REPORT_weak_skill_audit","label":"Weak Skill Visual Audit","file_type":"document","source_file":"AUDIT_REPORT.md","source_location":null,"source_url":null,"captured_at":null,"author":null,"contributor":null},{"id":"ADR005_reading_stimuli","label":"Readings as Skill Training Stimuli (ADR-005)","file_type":"document","source_file":"decisions/ADR-005-reading-stimuli-for-skill-training.md","source_location":null,"source_url":null,"captured_at":null,"author":null,"contributor":null},{"id":"ADR006_progress_identity","label":"Progress Identity and Cohort Licensing (ADR-006)","file_type":"document","source_file":"decisions/ADR-006-progress-identity-and-future-cohort-licensing.md","source_location":null,"source_url":null,"captured_at":null,"author":null,"contributor":null},{"id":"INGENIUM_platform","label":"INGENIUM Platform","file_type":"document","source_file":"README.md","source_location":null,"source_url":null,"captured_at":null,"author":null,"contributor":null},{"id":"skill_first_model","label":"Skill-First Training Model","file_type":"concept","source_file":"docs/02_pedagogical_model/learning_model.md","source_location":null,"source_url":null,"captured_at":null,"author":null,"contributor":null},{"id":"mastery_model_state_machine","label":"Mastery Model State Machine","file_type":"concept","source_file":"tests/e2e/WEAK_SKILL_TEST_SCHEMA.md","source_location":null,"source_url":null,"captured_at":null,"author":null,"contributor":null},{"id":"mastery_score_formula","label":"Mastery Score Formula","file_type":"concept","source_file":"tests/e2e/WEAK_SKILL_TEST_SCHEMA.md","source_location":null,"source_url":null,"captured_at":null,"author":null,"contributor":null},{"id":"get_next_step_recommendation","label":"getNextStepRecommendation","file_type":"concept","source_file":"tests/e2e/WEAK_SKILL_TEST_SCHEMA.md","source_location":null,"source_url":null,"captured_at":null,"author":null,"contributor":null},{"id":"build_mastery_model","label":"buildMasteryModel","file_type":"concept","source_file":"docs/continuar-pc-trabajo.md","source_location":null,"source_url":null,"captured_at":null,"author":null,"contributor":null},{"id":"text_group_stimulus","label":"TextGroup as Internal Stimulus","file_type":"concept","source_file":"decisions/ADR-005-reading-stimuli-for-skill-training.md","source_location":null,"source_url":null,"captured_at":null,"author":null,"contributor":null},{"id":"progress_code_identity","label":"Progress Code Identity","file_type":"concept","source_file":"decisions/ADR-006-progress-identity-and-future-cohort-licensing.md","source_location":null,"source_url":null,"captured_at":null,"author":null,"contributor":null},{"id":"cohort_licensing","label":"Cohort Licensing (Future)","file_type":"concept","source_file":"decisions/ADR-006-progress-identity-and-future-cohort-licensing.md","source_location":null,"source_url":null,"captured_at":null,"author":null,"contributor":null},{"id":"skills_map_lengua","label":"Lengua Skills Map (7 Skills)","file_type":"document","source_file":"docs/03_skill_system/skills_map.md","source_location":null,"source_url":null,"captured_at":null,"author":null,"contributor":null},{"id":"exercise_types","label":"Exercise Types (multiple_choice, completion, ordering, highlight_selection, categorization)","file_type":"concept","source_file":"docs/03_skill_system/skills_map.md","source_location":null,"source_url":null,"captured_at":null,"author":null,"contributor":null},{"id":"pedagogical_model","label":"Pedagogical Model","file_type":"document","source_file":"docs/02_pedagogical_model/learning_model.md","source_location":null,"source_url":null,"captured_at":null,"author":null,"contributor":null},{"id":"feedback_principles","label":"Feedback Principles (immediate, brief, actionable, skill-linked)","file_type":"concept","source_file":"docs/02_pedagogical_model/learning_model.md","source_location":null,"source_url":null,"captured_at":null,"author":null,"contributor":null},{"id":"cognitive_load_rules","label":"Cognitive Load Rules","file_type":"concept","source_file":"docs/02_pedagogical_model/learning_model.md","source_location":null,"source_url":null,"captured_at":null,"author":null,"contributor":null},{"id":"trainable_skills","label":"trainable_skills Criterion","file_type":"concept","source_file":"decisions/ADR-005-reading-stimuli-for-skill-training.md","source_location":null,"source_url":null,"captured_at":null,"author":null,"contributor":null},{"id":"module_fit","label":"module_fit Label","file_type":"concept","source_file":"decisions/ADR-005-reading-stimuli-for-skill-training.md","source_location":null,"source_url":null,"captured_at":null,"author":null,"contributor":null},{"id":"skill_states","label":"Skill States (Weak/Developing/Mastered/Mastered+)","file_type":"concept","source_file":"tests/e2e/WEAK_SKILL_TEST_SCHEMA.md","source_location":null,"source_url":null,"captured_at":null,"author":null,"contributor":null},{"id":"weak_skill_strengthening","label":"Weak Skill Strengthening Flow","file_type":"concept","source_file":"tests/e2e/WEAK_SKILL_TEST_SCHEMA.md","source_location":null,"source_url":null,"captured_at":null,"author":null,"contributor":null},{"id":"action_panel_cta","label":"ActionPanel CTA","file_type":"concept","source_file":"AUDIT_REPORT.md","source_location":null,"source_url":null,"captured_at":null,"author":null,"contributor":null},{"id":"improvement_panel","label":"ImprovementPanel (Weakness Panel)","file_type":"concept","source_file":"AUDIT_REPORT.md","source_location":null,"source_url":null,"captured_at":null,"author":null,"contributor":null},{"id":"empty_state_ui","label":"Empty State UI","file_type":"concept","source_file":"AUDIT_REPORT.md","source_location":null,"source_url":null,"captured_at":null,"author":null,"contributor":null},{"id":"simulation_page","label":"Simulation Page","file_type":"concept","source_file":"AUDIT_REPORT.md","source_location":null,"source_url":null,"captured_at":null,"author":null,"contributor":null},{"id":"human_readable_mastery_messages","label":"Human-Readable Mastery Messages","file_type":"concept","source_file":"AUDIT_REPORT.md","source_location":null,"source_url":null,"captured_at":null,"author":null,"contributor":null},{"id":"e2e_weak_skill_test","label":"E2E Weak Skill Test","file_type":"document","source_file":"tests/e2e/WEAK_SKILL_TEST_SCHEMA.md","source_location":null,"source_url":null,"captured_at":null,"author":null,"contributor":null},{"id":"audit_weak_skill_ui_test","label":"Audit Weak Skill UI Test","file_type":"document","source_file":"AUDIT_REPORT.md","source_location":null,"source_url":null,"captured_at":null,"author":null,"contributor":null},{"id":"simulator_readiness","label":"Simulator Readiness Conditions","file_type":"concept","source_file":"tests/e2e/WEAK_SKILL_TEST_SCHEMA.md","source_location":null,"source_url":null,"captured_at":null,"author":null,"contributor":null},{"id":"product_roadmap","label":"Product Roadmap","file_type":"document","source_file":"roadmap/roadmap.md","source_location":null,"source_url":null,"captured_at":null,"author":null,"contributor":null},{"id":"continuar_pc_trabajo","label":"Continue on Work PC Guide","file_type":"document","source_file":"docs/continuar-pc-trabajo.md","source_location":null,"source_url":null,"captured_at":null,"author":null,"contributor":null},{"id":"reading_as_stimulus_rationale","label":"Reading as Stimulus Rationale","file_type":"concept","source_file":"docs/02_pedagogical_model/learning_model.md","source_location":null,"source_url":null,"captured_at":null,"author":null,"contributor":null},{"id":"progress_license_separation_rationale","label":"Progress/License Separation Rationale","file_type":"concept","source_file":"decisions/ADR-006-progress-identity-and-future-cohort-licensing.md","source_location":null,"source_url":null,"captured_at":null,"author":null,"contributor":null}],"edges":[{"source":"ADR005_reading_stimuli","target":"skill_first_model","relation":"rationale_for","confidence":"EXTRACTED","confidence_score":1.0,"source_file":"decisions/ADR-005-reading-stimuli-for-skill-training.md","source_location":null,"weight":1.0},{"source":"ADR005_reading_stimuli","target":"text_group_stimulus","relation":"conceptually_related_to","confidence":"EXTRACTED","confidence_score":1.0,"source_file":"decisions/ADR-005-reading-stimuli-for-skill-training.md","source_location":null,"weight":1.0},{"source":"ADR005_reading_stimuli","target":"trainable_skills","relation":"references","confidence":"EXTRACTED","confidence_score":1.0,"source_file":"decisions/ADR-005-reading-stimuli-for-skill-training.md","source_location":null,"weight":1.0},{"source":"ADR005_reading_stimuli","target":"module_fit","relation":"references","confidence":"EXTRACTED","confidence_score":1.0,"source_file":"decisions/ADR-005-reading-stimuli-for-skill-training.md","source_location":null,"weight":1.0},{"source":"ADR005_reading_stimuli","target":"reading_as_stimulus_rationale","relation":"conceptually_related_to","confidence":"EXTRACTED","confidence_score":1.0,"source_file":"decisions/ADR-005-reading-stimuli-for-skill-training.md","source_location":null,"weight":1.0},{"source":"reading_as_stimulus_rationale","target":"text_group_stimulus","relation":"rationale_for","confidence":"INFERRED","confidence_score":0.85,"source_file":"docs/02_pedagogical_model/learning_model.md","source_location":null,"weight":1.0},{"source":"ADR006_progress_identity","target":"progress_code_identity","relation":"conceptually_related_to","confidence":"EXTRACTED","confidence_score":1.0,"source_file":"decisions/ADR-006-progress-identity-and-future-cohort-licensing.md","source_location":null,"weight":1.0},{"source":"ADR006_progress_identity","target":"cohort_licensing","relation":"conceptually_related_to","confidence":"EXTRACTED","confidence_score":1.0,"source_file":"decisions/ADR-006-progress-identity-and-future-cohort-licensing.md","source_location":null,"weight":1.0},{"source":"ADR006_progress_identity","target":"progress_license_separation_rationale","relation":"conceptually_related_to","confidence":"EXTRACTED","confidence_score":1.0,"source_file":"decisions/ADR-006-progress-identity-and-future-cohort-licensing.md","source_location":null,"weight":1.0},{"source":"progress_license_separation_rationale","target":"progress_code_identity","relation":"rationale_for","confidence":"INFERRED","confidence_score":0.85,"source_file":"decisions/ADR-006-progress-identity-and-future-cohort-licensing.md","source_location":null,"weight":1.0},{"source":"progress_license_separation_rationale","target":"cohort_licensing","relation":"rationale_for","confidence":"INFERRED","confidence_score":0.8,"source_file":"decisions/ADR-006-progress-identity-and-future-cohort-licensing.md","source_location":null,"weight":1.0},{"source":"mastery_model_state_machine","target":"skill_states","relation":"implements","confidence":"EXTRACTED","confidence_score":1.0,"source_file":"tests/e2e/WEAK_SKILL_TEST_SCHEMA.md","source_location":null,"weight":1.0},{"source":"mastery_model_state_machine","target":"mastery_score_formula","relation":"implements","confidence":"EXTRACTED","confidence_score":1.0,"source_file":"tests/e2e/WEAK_SKILL_TEST_SCHEMA.md","source_location":null,"weight":1.0},{"source":"get_next_step_recommendation","target":"mastery_model_state_machine","relation":"calls","confidence":"EXTRACTED","confidence_score":1.0,"source_file":"tests/e2e/WEAK_SKILL_TEST_SCHEMA.md","source_location":null,"weight":1.0},{"source":"get_next_step_recommendation","target":"simulator_readiness","relation":"references","confidence":"EXTRACTED","confidence_score":1.0,"source_file":"tests/e2e/WEAK_SKILL_TEST_SCHEMA.md","source_location":null,"weight":1.0},{"source":"get_next_step_recommendation","target":"weak_skill_strengthening","relation":"conceptually_related_to","confidence":"EXTRACTED","confidence_score":1.0,"source_file":"tests/e2e/WEAK_SKILL_TEST_SCHEMA.md","source_location":null,"weight":1.0},{"source":"weak_skill_strengthening","target":"mastery_model_state_machine","relation":"references","confidence":"EXTRACTED","confidence_score":1.0,"source_file":"tests/e2e/WEAK_SKILL_TEST_SCHEMA.md","source_location":null,"weight":1.0},{"source":"weak_skill_strengthening","target":"get_next_step_recommendation","relation":"references","confidence":"EXTRACTED","confidence_score":1.0,"source_file":"tests/e2e/WEAK_SKILL_TEST_SCHEMA.md","source_location":null,"weight":1.0},{"source":"action_panel_cta","target":"get_next_step_recommendation","relation":"calls","confidence":"EXTRACTED","confidence_score":1.0,"source_file":"AUDIT_REPORT.md","source_location":null,"weight":1.0},{"source":"improvement_panel","target":"mastery_model_state_machine","relation":"calls","confidence":"EXTRACTED","confidence_score":1.0,"source_file":"AUDIT_REPORT.md","source_location":null,"weight":1.0},{"source":"human_readable_mastery_messages","target":"skill_states","relation":"implements","confidence":"INFERRED","confidence_score":0.8,"source_file":"AUDIT_REPORT.md","source_location":null,"weight":1.0},{"source":"human_readable_mastery_messages","target":"improvement_panel","relation":"conceptually_related_to","confidence":"EXTRACTED","confidence_score":1.0,"source_file":"AUDIT_REPORT.md","source_location":null,"weight":1.0},{"source":"e2e_weak_skill_test","target":"mastery_model_state_machine","relation":"references","confidence":"EXTRACTED","confidence_score":1.0,"source_file":"tests/e2e/WEAK_SKILL_TEST_SCHEMA.md","source_location":null,"weight":1.0},{"source":"e2e_weak_skill_test","target":"get_next_step_recommendation","relation":"references","confidence":"EXTRACTED","confidence_score":1.0,"source_file":"tests/e2e/WEAK_SKILL_TEST_SCHEMA.md","source_location":null,"weight":1.0},{"source":"e2e_weak_skill_test","target":"weak_skill_strengthening","relation":"references","confidence":"EXTRACTED","confidence_score":1.0,"source_file":"tests/e2e/WEAK_SKILL_TEST_SCHEMA.md","source_location":null,"weight":1.0},{"source":"audit_weak_skill_ui_test","target":"improvement_panel","relation":"references","confidence":"EXTRACTED","confidence_score":1.0,"source_file":"AUDIT_REPORT.md","source_location":null,"weight":1.0},{"source":"audit_weak_skill_ui_test","target":"action_panel_cta","relation":"references","confidence":"EXTRACTED","confidence_score":1.0,"source_file":"AUDIT_REPORT.md","source_location":null,"weight":1.0},{"source":"audit_weak_skill_ui_test","target":"empty_state_ui","relation":"references","confidence":"EXTRACTED","confidence_score":1.0,"source_file":"AUDIT_REPORT.md","source_location":null,"weight":1.0},{"source":"audit_weak_skill_ui_test","target":"simulation_page","relation":"references","confidence":"EXTRACTED","confidence_score":1.0,"source_file":"AUDIT_REPORT.md","source_location":null,"weight":1.0},{"source":"pedagogical_model","target":"skill_first_model","relation":"conceptually_related_to","confidence":"EXTRACTED","confidence_score":1.0,"source_file":"docs/02_pedagogical_model/learning_model.md","source_location":null,"weight":1.0},{"source":"pedagogical_model","target":"feedback_principles","relation":"conceptually_related_to","confidence":"EXTRACTED","confidence_score":1.0,"source_file":"docs/02_pedagogical_model/learning_model.md","source_location":null,"weight":1.0},{"source":"pedagogical_model","target":"cognitive_load_rules","relation":"conceptually_related_to","confidence":"EXTRACTED","confidence_score":1.0,"source_file":"docs/02_pedagogical_model/learning_model.md","source_location":null,"weight":1.0},{"source":"pedagogical_model","target":"reading_as_stimulus_rationale","relation":"conceptually_related_to","confidence":"EXTRACTED","confidence_score":1.0,"source_file":"docs/02_pedagogical_model/learning_model.md","source_location":null,"weight":1.0},{"source":"reading_as_stimulus_rationale","target":"skill_first_model","relation":"rationale_for","confidence":"INFERRED","confidence_score":0.9,"source_file":"docs/02_pedagogical_model/learning_model.md","source_location":null,"weight":1.0},{"source":"skills_map_lengua","target":"exercise_types","relation":"references","confidence":"EXTRACTED","confidence_score":1.0,"source_file":"docs/03_skill_system/skills_map.md","source_location":null,"weight":1.0},{"source":"skills_map_lengua","target":"skill_first_model","relation":"conceptually_related_to","confidence":"EXTRACTED","confidence_score":1.0,"source_file":"docs/03_skill_system/skills_map.md","source_location":null,"weight":1.0},{"source":"INGENIUM_platform","target":"skill_first_model","relation":"conceptually_related_to","confidence":"EXTRACTED","confidence_score":1.0,"source_file":"README.md","source_location":null,"weight":1.0},{"source":"INGENIUM_platform","target":"build_mastery_model","relation":"references","confidence":"EXTRACTED","confidence_score":1.0,"source_file":"README.md","source_location":null,"weight":1.0},{"source":"INGENIUM_platform","target":"get_next_step_recommendation","relation":"references","confidence":"EXTRACTED","confidence_score":1.0,"source_file":"README.md","source_location":null,"weight":1.0},{"source":"INGENIUM_platform","target":"skills_map_lengua","relation":"conceptually_related_to","confidence":"EXTRACTED","confidence_score":1.0,"source_file":"README.md","source_location":null,"weight":1.0},{"source":"continuar_pc_trabajo","target":"build_mastery_model","relation":"references","confidence":"EXTRACTED","confidence_score":1.0,"source_file":"docs/continuar-pc-trabajo.md","source_location":null,"weight":1.0},{"source":"continuar_pc_trabajo","target":"get_next_step_recommendation","relation":"references","confidence":"EXTRACTED","confidence_score":1.0,"source_file":"docs/continuar-pc-trabajo.md","source_location":null,"weight":1.0},{"source":"build_mastery_model","target":"mastery_model_state_machine","relation":"implements","confidence":"INFERRED","confidence_score":0.85,"source_file":"docs/continuar-pc-trabajo.md","source_location":null,"weight":1.0},{"source":"product_roadmap","target":"progress_code_identity","relation":"references","confidence":"EXTRACTED","confidence_score":1.0,"source_file":"roadmap/roadmap.md","source_location":null,"weight":1.0},{"source":"product_roadmap","target":"cohort_licensing","relation":"references","confidence":"EXTRACTED","confidence_score":1.0,"source_file":"roadmap/roadmap.md","source_location":null,"weight":1.0},{"source":"product_roadmap","target":"simulator_readiness","relation":"references","confidence":"INFERRED","confidence_score":0.7,"source_file":"roadmap/roadmap.md","source_location":null,"weight":1.0},{"source":"module_fit","target":"trainable_skills","relation":"semantically_similar_to","confidence":"INFERRED","confidence_score":0.75,"source_file":"decisions/ADR-005-reading-stimuli-for-skill-training.md","source_location":null,"weight":1.0},{"source":"ADR006_progress_identity","target":"skill_first_model","relation":"conceptually_related_to","confidence":"INFERRED","confidence_score":0.7,"source_file":"decisions/ADR-006-progress-identity-and-future-cohort-licensing.md","source_location":null,"weight":1.0},{"source":"action_panel_cta","target":"weak_skill_strengthening","relation":"conceptually_related_to","confidence":"INFERRED","confidence_score":0.8,"source_file":"AUDIT_REPORT.md","source_location":null,"weight":1.0},{"source":"empty_state_ui","target":"skill_states","relation":"conceptually_related_to","confidence":"INFERRED","confidence_score":0.7,"source_file":"AUDIT_REPORT.md","source_location":null,"weight":1.0},{"source":"simulation_page","target":"simulator_readiness","relation":"conceptually_related_to","confidence":"INFERRED","confidence_score":0.8,"source_file":"AUDIT_REPORT.md","source_location":null,"weight":1.0},{"source":"skill_first_model","target":"text_group_stimulus","relation":"conceptually_related_to","confidence":"INFERRED","confidence_score":0.85,"source_file":"docs/02_pedagogical_model/learning_model.md","source_location":null,"weight":1.0},{"source":"feedback_principles","target":"human_readable_mastery_messages","relation":"semantically_similar_to","confidence":"INFERRED","confidence_score":0.7,"source_file":"docs/02_pedagogical_model/learning_model.md","source_location":null,"weight":1.0},{"source":"AUDIT_REPORT_weak_skill_audit","target":"audit_weak_skill_ui_test","relation":"references","confidence":"EXTRACTED","confidence_score":1.0,"source_file":"AUDIT_REPORT.md","source_location":null,"weight":1.0},{"source":"AUDIT_REPORT_weak_skill_audit","target":"human_readable_mastery_messages","relation":"conceptually_related_to","confidence":"EXTRACTED","confidence_score":1.0,"source_file":"AUDIT_REPORT.md","source_location":null,"weight":1.0},{"source":"AUDIT_REPORT_weak_skill_audit","target":"action_panel_cta","relation":"conceptually_related_to","confidence":"EXTRACTED","confidence_score":1.0,"source_file":"AUDIT_REPORT.md","source_location":null,"weight":1.0},{"source":"ADR005_reading_stimuli","target":"pedagogical_model","relation":"cites","confidence":"EXTRACTED","confidence_score":1.0,"source_file":"decisions/ADR-005-reading-stimuli-for-skill-training.md","source_location":null,"weight":1.0}],"hyperedges":[{"id":"he_weak_skill_strengthening_system","label":"Weak Skill Strengthening System","nodes":["mastery_model_state_machine","get_next_step_recommendation","skill_states"],"description":"The mastery model state machine, recommendation engine, and skill states together form the weak skill detection, prioritization, and reinforcement system.","source_file":"tests/e2e/WEAK_SKILL_TEST_SCHEMA.md"},{"id":"he_pedagogical_core_principles","label":"Pedagogical Core Principles","nodes":["skill_first_model","feedback_principles","cognitive_load_rules"],"description":"Three core pedagogical principles that govern all content and exercise design: skill-first priority, immediate actionable feedback, and cognitive load management.","source_file":"docs/02_pedagogical_model/learning_model.md"},{"id":"he_reading_stimulus_decision","label":"Reading Stimulus Design Decision","nodes":["skill_first_model","text_group_stimulus","trainable_skills"],"description":"ADR-005 establishes that readings serve as internal stimuli subordinate to skill-first selection, with trainable_skills as the primary acceptance criterion overriding module_fit.","source_file":"decisions/ADR-005-reading-stimuli-for-skill-training.md"}],"input_tokens":0,"output_tokens":0}