{"nodes": [{"id": "src_practice_session_runner_ts", "label": "session_runner.ts", "file_type": "code", "source_file": "src\\practice\\session_runner.ts", "source_location": "L1"}, {"id": "session_runner_toselectorexercise", "label": "toSelectorExercise()", "file_type": "code", "source_file": "src\\practice\\session_runner.ts", "source_location": "L78"}, {"id": "session_runner_loadexercises", "label": "loadExercises()", "file_type": "code", "source_file": "src\\practice\\session_runner.ts", "source_location": "L87"}, {"id": "session_runner_evaluateanswer", "label": "evaluateAnswer()", "file_type": "code", "source_file": "src\\practice\\session_runner.ts", "source_location": "L99"}, {"id": "session_runner_computeaccuracy", "label": "computeAccuracy()", "file_type": "code", "source_file": "src\\practice\\session_runner.ts", "source_location": "L103"}, {"id": "session_runner_computestreak", "label": "computeStreak()", "file_type": "code", "source_file": "src\\practice\\session_runner.ts", "source_location": "L112"}, {"id": "session_runner_builduserstate", "label": "buildUserState()", "file_type": "code", "source_file": "src\\practice\\session_runner.ts", "source_location": "L127"}, {"id": "session_runner_findexercise", "label": "findExercise()", "file_type": "code", "source_file": "src\\practice\\session_runner.ts", "source_location": "L143"}, {"id": "session_runner_runsession", "label": "runSession()", "file_type": "code", "source_file": "src\\practice\\session_runner.ts", "source_location": "L153"}, {"id": "session_runner_rundeterministicsession", "label": "runDeterministicSession()", "file_type": "code", "source_file": "src\\practice\\session_runner.ts", "source_location": "L267"}, {"id": "session_runner_runmixedsession", "label": "runMixedSession()", "file_type": "code", "source_file": "src\\practice\\session_runner.ts", "source_location": "L276"}, {"id": "session_runner_startpracticesession", "label": "startPracticeSession()", "file_type": "code", "source_file": "src\\practice\\session_runner.ts", "source_location": "L289"}], "edges": [{"source": "src_practice_session_runner_ts", "target": "node_fs", "relation": "imports_from", "confidence": "EXTRACTED", "source_file": "src\\practice\\session_runner.ts", "source_location": "L1", "weight": 1.0}, {"source": "src_practice_session_runner_ts", "target": "node_path", "relation": "imports_from", "confidence": "EXTRACTED", "source_file": "src\\practice\\session_runner.ts", "source_location": "L2", "weight": 1.0}, {"source": "src_practice_session_runner_ts", "target": "src_practice_exercise_selector_ts", "relation": "imports_from", "confidence": "EXTRACTED", "source_file": "src\\practice\\session_runner.ts", "source_location": "L3", "weight": 1.0}, {"source": "src_practice_session_runner_ts", "target": "session_runner_toselectorexercise", "relation": "contains", "confidence": "EXTRACTED", "source_file": "src\\practice\\session_runner.ts", "source_location": "L78", "weight": 1.0}, {"source": "src_practice_session_runner_ts", "target": "session_runner_loadexercises", "relation": "contains", "confidence": "EXTRACTED", "source_file": "src\\practice\\session_runner.ts", "source_location": "L87", "weight": 1.0}, {"source": "src_practice_session_runner_ts", "target": "session_runner_evaluateanswer", "relation": "contains", "confidence": "EXTRACTED", "source_file": "src\\practice\\session_runner.ts", "source_location": "L99", "weight": 1.0}, {"source": "src_practice_session_runner_ts", "target": "session_runner_computeaccuracy", "relation": "contains", "confidence": "EXTRACTED", "source_file": "src\\practice\\session_runner.ts", "source_location": "L103", "weight": 1.0}, {"source": "src_practice_session_runner_ts", "target": "session_runner_computestreak", "relation": "contains", "confidence": "EXTRACTED", "source_file": "src\\practice\\session_runner.ts", "source_location": "L112", "weight": 1.0}, {"source": "src_practice_session_runner_ts", "target": "session_runner_builduserstate", "relation": "contains", "confidence": "EXTRACTED", "source_file": "src\\practice\\session_runner.ts", "source_location": "L127", "weight": 1.0}, {"source": "src_practice_session_runner_ts", "target": "session_runner_findexercise", "relation": "contains", "confidence": "EXTRACTED", "source_file": "src\\practice\\session_runner.ts", "source_location": "L143", "weight": 1.0}, {"source": "src_practice_session_runner_ts", "target": "session_runner_runsession", "relation": "contains", "confidence": "EXTRACTED", "source_file": "src\\practice\\session_runner.ts", "source_location": "L153", "weight": 1.0}, {"source": "src_practice_session_runner_ts", "target": "session_runner_rundeterministicsession", "relation": "contains", "confidence": "EXTRACTED", "source_file": "src\\practice\\session_runner.ts", "source_location": "L267", "weight": 1.0}, {"source": "src_practice_session_runner_ts", "target": "session_runner_runmixedsession", "relation": "contains", "confidence": "EXTRACTED", "source_file": "src\\practice\\session_runner.ts", "source_location": "L276", "weight": 1.0}, {"source": "src_practice_session_runner_ts", "target": "session_runner_startpracticesession", "relation": "contains", "confidence": "EXTRACTED", "source_file": "src\\practice\\session_runner.ts", "source_location": "L289", "weight": 1.0}, {"source": "session_runner_builduserstate", "target": "session_runner_computeaccuracy", "relation": "calls", "confidence": "EXTRACTED", "source_file": "src\\practice\\session_runner.ts", "source_location": "L136", "weight": 1.0}, {"source": "session_runner_builduserstate", "target": "session_runner_computestreak", "relation": "calls", "confidence": "EXTRACTED", "source_file": "src\\practice\\session_runner.ts", "source_location": "L137", "weight": 1.0}, {"source": "session_runner_runsession", "target": "session_runner_findexercise", "relation": "calls", "confidence": "EXTRACTED", "source_file": "src\\practice\\session_runner.ts", "source_location": "L179", "weight": 1.0}, {"source": "session_runner_runsession", "target": "session_runner_evaluateanswer", "relation": "calls", "confidence": "EXTRACTED", "source_file": "src\\practice\\session_runner.ts", "source_location": "L182", "weight": 1.0}, {"source": "session_runner_runsession", "target": "session_runner_builduserstate", "relation": "calls", "confidence": "EXTRACTED", "source_file": "src\\practice\\session_runner.ts", "source_location": "L206", "weight": 1.0}, {"source": "session_runner_rundeterministicsession", "target": "session_runner_loadexercises", "relation": "calls", "confidence": "EXTRACTED", "source_file": "src\\practice\\session_runner.ts", "source_location": "L269", "weight": 1.0}, {"source": "session_runner_rundeterministicsession", "target": "session_runner_runsession", "relation": "calls", "confidence": "EXTRACTED", "source_file": "src\\practice\\session_runner.ts", "source_location": "L273", "weight": 1.0}, {"source": "session_runner_runmixedsession", "target": "session_runner_loadexercises", "relation": "calls", "confidence": "EXTRACTED", "source_file": "src\\practice\\session_runner.ts", "source_location": "L278", "weight": 1.0}, {"source": "session_runner_runmixedsession", "target": "session_runner_runsession", "relation": "calls", "confidence": "EXTRACTED", "source_file": "src\\practice\\session_runner.ts", "source_location": "L286", "weight": 1.0}, {"source": "session_runner_startpracticesession", "target": "session_runner_loadexercises", "relation": "calls", "confidence": "EXTRACTED", "source_file": "src\\practice\\session_runner.ts", "source_location": "L293", "weight": 1.0}, {"source": "session_runner_startpracticesession", "target": "session_runner_findexercise", "relation": "calls", "confidence": "EXTRACTED", "source_file": "src\\practice\\session_runner.ts", "source_location": "L304", "weight": 1.0}], "raw_calls": [{"caller_nid": "session_runner_loadexercises", "callee": "readFileSync", "source_file": "src\\practice\\session_runner.ts", "source_location": "L88"}, {"caller_nid": "session_runner_loadexercises", "callee": "parse", "source_file": "src\\practice\\session_runner.ts", "source_location": "L89"}, {"caller_nid": "session_runner_loadexercises", "callee": "isArray", "source_file": "src\\practice\\session_runner.ts", "source_location": "L90"}, {"caller_nid": "session_runner_computeaccuracy", "callee": "filter", "source_file": "src\\practice\\session_runner.ts", "source_location": "L104"}, {"caller_nid": "session_runner_computeaccuracy", "callee": "filter", "source_file": "src\\practice\\session_runner.ts", "source_location": "L108"}, {"caller_nid": "session_runner_computestreak", "callee": "filter", "source_file": "src\\practice\\session_runner.ts", "source_location": "L113"}, {"caller_nid": "session_runner_findexercise", "callee": "find", "source_file": "src\\practice\\session_runner.ts", "source_location": "L144"}, {"caller_nid": "session_runner_runsession", "callee": "map", "source_file": "src\\practice\\session_runner.ts", "source_location": "L159"}, {"caller_nid": "session_runner_runsession", "callee": "log", "source_file": "src\\practice\\session_runner.ts", "source_location": "L164"}, {"caller_nid": "session_runner_runsession", "callee": "log", "source_file": "src\\practice\\session_runner.ts", "source_location": "L165"}, {"caller_nid": "session_runner_runsession", "callee": "log", "source_file": "src\\practice\\session_runner.ts", "source_location": "L166"}, {"caller_nid": "session_runner_runsession", "callee": "log", "source_file": "src\\practice\\session_runner.ts", "source_location": "L167"}, {"caller_nid": "session_runner_runsession", "callee": "selectNextExerciseDetailed", "source_file": "src\\practice\\session_runner.ts", "source_location": "L174"}, {"caller_nid": "session_runner_runsession", "callee": "availableExercises", "source_file": "src\\practice\\session_runner.ts", "source_location": "L174"}, {"caller_nid": "session_runner_runsession", "callee": "add", "source_file": "src\\practice\\session_runner.ts", "source_location": "L180"}, {"caller_nid": "session_runner_runsession", "callee": "answerProvider", "source_file": "src\\practice\\session_runner.ts", "source_location": "L181"}, {"caller_nid": "session_runner_runsession", "callee": "log", "source_file": "src\\practice\\session_runner.ts", "source_location": "L186"}, {"caller_nid": "session_runner_runsession", "callee": "log", "source_file": "src\\practice\\session_runner.ts", "source_location": "L187"}, {"caller_nid": "session_runner_runsession", "callee": "log", "source_file": "src\\practice\\session_runner.ts", "source_location": "L188"}, {"caller_nid": "session_runner_runsession", "callee": "log", "source_file": "src\\practice\\session_runner.ts", "source_location": "L189"}, {"caller_nid": "session_runner_runsession", "callee": "log", "source_file": "src\\practice\\session_runner.ts", "source_location": "L190"}, {"caller_nid": "session_runner_runsession", "callee": "log", "source_file": "src\\practice\\session_runner.ts", "source_location": "L191"}, {"caller_nid": "session_runner_runsession", "callee": "log", "source_file": "src\\practice\\session_runner.ts", "source_location": "L192"}, {"caller_nid": "session_runner_runsession", "callee": "log", "source_file": "src\\practice\\session_runner.ts", "source_location": "L193"}, {"caller_nid": "session_runner_runsession", "callee": "push", "source_file": "src\\practice\\session_runner.ts", "source_location": "L195"}, {"caller_nid": "session_runner_runsession", "callee": "selectNextExerciseDetailed", "source_file": "src\\practice\\session_runner.ts", "source_location": "L209"}, {"caller_nid": "session_runner_runsession", "callee": "availableExercises", "source_file": "src\\practice\\session_runner.ts", "source_location": "L209"}, {"caller_nid": "session_runner_runsession", "callee": "filter", "source_file": "src\\practice\\session_runner.ts", "source_location": "L215"}, {"caller_nid": "session_runner_runsession", "callee": "log", "source_file": "src\\practice\\session_runner.ts", "source_location": "L218"}, {"caller_nid": "session_runner_runsession", "callee": "log", "source_file": "src\\practice\\session_runner.ts", "source_location": "L219"}, {"caller_nid": "session_runner_runsession", "callee": "log", "source_file": "src\\practice\\session_runner.ts", "source_location": "L220"}, {"caller_nid": "session_runner_runsession", "callee": "log", "source_file": "src\\practice\\session_runner.ts", "source_location": "L221"}, {"caller_nid": "session_runner_runsession", "callee": "log", "source_file": "src\\practice\\session_runner.ts", "source_location": "L222"}, {"caller_nid": "session_runner_runsession", "callee": "log", "source_file": "src\\practice\\session_runner.ts", "source_location": "L223"}, {"caller_nid": "session_runner_runsession", "callee": "round", "source_file": "src\\practice\\session_runner.ts", "source_location": "L223"}, {"caller_nid": "session_runner_runsession", "callee": "map", "source_file": "src\\practice\\session_runner.ts", "source_location": "L225"}, {"caller_nid": "session_runner_runsession", "callee": "log", "source_file": "src\\practice\\session_runner.ts", "source_location": "L226"}, {"caller_nid": "session_runner_runsession", "callee": "filter", "source_file": "src\\practice\\session_runner.ts", "source_location": "L229"}, {"caller_nid": "session_runner_runsession", "callee": "filter", "source_file": "src\\practice\\session_runner.ts", "source_location": "L230"}, {"caller_nid": "session_runner_runsession", "callee": "round", "source_file": "src\\practice\\session_runner.ts", "source_location": "L231"}, {"caller_nid": "session_runner_runsession", "callee": "log", "source_file": "src\\practice\\session_runner.ts", "source_location": "L232"}, {"caller_nid": "session_runner_runsession", "callee": "map", "source_file": "src\\practice\\session_runner.ts", "source_location": "L235"}, {"caller_nid": "session_runner_runsession", "callee": "log", "source_file": "src\\practice\\session_runner.ts", "source_location": "L236"}, {"caller_nid": "session_runner_runsession", "callee": "split", "source_file": "src\\practice\\session_runner.ts", "source_location": "L239"}, {"caller_nid": "session_runner_runsession", "callee": "filter", "source_file": "src\\practice\\session_runner.ts", "source_location": "L240"}, {"caller_nid": "session_runner_runsession", "callee": "filter", "source_file": "src\\practice\\session_runner.ts", "source_location": "L241"}, {"caller_nid": "session_runner_runsession", "callee": "round", "source_file": "src\\practice\\session_runner.ts", "source_location": "L242"}, {"caller_nid": "session_runner_runsession", "callee": "log", "source_file": "src\\practice\\session_runner.ts", "source_location": "L244"}, {"caller_nid": "session_runner_runsession", "callee": "log", "source_file": "src\\practice\\session_runner.ts", "source_location": "L247"}, {"caller_nid": "session_runner_runsession", "callee": "log", "source_file": "src\\practice\\session_runner.ts", "source_location": "L248"}, {"caller_nid": "session_runner_runsession", "callee": "log", "source_file": "src\\practice\\session_runner.ts", "source_location": "L251"}, {"caller_nid": "session_runner_runsession", "callee": "round", "source_file": "src\\practice\\session_runner.ts", "source_location": "L252"}, {"caller_nid": "session_runner_startpracticesession", "callee": "filter", "source_file": "src\\practice\\session_runner.ts", "source_location": "L295"}, {"caller_nid": "session_runner_startpracticesession", "callee": "filter", "source_file": "src\\practice\\session_runner.ts", "source_location": "L298"}, {"caller_nid": "session_runner_startpracticesession", "callee": "map", "source_file": "src\\practice\\session_runner.ts", "source_location": "L302"}, {"caller_nid": "session_runner_startpracticesession", "callee": "selectNextExerciseDetailed", "source_file": "src\\practice\\session_runner.ts", "source_location": "L303"}]}