{"nodes": [{"id": "src_components_dashboard_actionpanel_tsx", "label": "ActionPanel.tsx", "file_type": "code", "source_file": "src\\components\\dashboard\\ActionPanel.tsx", "source_location": "L1"}, {"id": "actionpanel_actionpanel", "label": "ActionPanel()", "file_type": "code", "source_file": "src\\components\\dashboard\\ActionPanel.tsx", "source_location": "L15"}], "edges": [{"source": "src_components_dashboard_actionpanel_tsx", "target": "link", "relation": "imports_from", "confidence": "EXTRACTED", "source_file": "src\\components\\dashboard\\ActionPanel.tsx", "source_location": "L1", "weight": 1.0}, {"source": "src_components_dashboard_actionpanel_tsx", "target": "src_components_dashboard_storage_local_progress_store", "relation": "imports_from", "confidence": "EXTRACTED", "source_file": "src\\components\\dashboard\\ActionPanel.tsx", "source_location": "L2", "weight": 1.0}, {"source": "src_components_dashboard_actionpanel_tsx", "target": "actionpanel_actionpanel", "relation": "contains", "confidence": "EXTRACTED", "source_file": "src\\components\\dashboard\\ActionPanel.tsx", "source_location": "L15", "weight": 1.0}], "raw_calls": [{"caller_nid": "actionpanel_actionpanel", "callee": "encodeURIComponent", "source_file": "src\\components\\dashboard\\ActionPanel.tsx", "source_location": "L16"}]}